pikendus_backend-0.2.8.dist-info/METADATA
pikendus_backend-0.2.8.dist-info/WHEEL
pikendus_backend-0.2.8.dist-info/entry_points.txt
pikendus_backend-0.2.8.dist-info/licenses/LICENSE
pikendus_backend/PikendusWheelBuilder.py
pikendus_backend/__init__.py
pikendus_backend/__main__.py
pikendus_backend/compile.py
pikendus_backend/gene_py_src.py
pikendus_backend/ligne_debug.py
pikendus_backend/main.py
pikendus_backend/structure.py
pikendus_backend-0.2.8.dist-info/RECORD
